cascade_config.py
cascade_config-0.4.0.dist-info/LICENSE
cascade_config-0.4.0.dist-info/WHEEL
cascade_config-0.4.0.dist-info/METADATA
cascade_config-0.4.0.dist-info/RECORD
