Metadata-Version: 2.1
Name: cascade-config
Version: 0.4.0
Summary: Cascading configuration from the CLI and config files.
Keywords: configuration,command line interface,configuration files,JSON
Author-email: Ralf Gabriels <ralf@gabriels.dev>
Requires-Python: >=3.6
Classifier: License :: OSI Approved :: Apache Software License
Classifier: Intended Audience :: Developers
Classifier: Operating System :: OS Independent
Classifier: Programming Language :: Python :: 3
Classifier: Topic :: Software Development
Classifier: Topic :: Utilities
Requires-Dist: jsonschema>=3
Requires-Dist: sphinx ; extra == "docs"
Requires-Dist: numpydoc>=1,<2 ; extra == "docs"
Requires-Dist: recommonmark ; extra == "docs"
Requires-Dist: sphinx-mdinclude ; extra == "docs"
Requires-Dist: toml ; extra == "docs"
Requires-Dist: semver>=2 ; extra == "docs"
Requires-Dist: sphinx_rtd_theme ; extra == "docs"
Requires-Dist: sphinx-autobuild ; extra == "docs"
Requires-Dist: pytest>=6,<7 ; extra == "test"
Requires-Dist: pytest-cov>=2,<3 ; extra == "test"
Project-URL: GitHub, https://github.com/RalfG/cascade-config
Project-URL: ReadTheDocs, https://cascade-config.readthedocs.io/en/stable/
Provides-Extra: docs
Provides-Extra: test
